baikes/__init__.py
baikes/__main__.py
baikes/baike.py
baikes/provider.py
baikes-0.1.4.dist-info/License
baikes-0.1.4.dist-info/METADATA
baikes-0.1.4.dist-info/WHEEL
baikes-0.1.4.dist-info/top_level.txt
baikes-0.1.4.dist-info/RECORD
