Metadata-Version: 2.1
Name: baikes
Version: 0.1.4
Summary: 百度百科简易爬虫
Home-page: https://github.com/Thexvoilone/baikes
Author: Voilone
Author-email: voilone@qq.com
License: MIT
Classifier: Development Status :: 5 - Production/Stable
Classifier: Intended Audience :: Developers
Classifier: Topic :: Utilities
Classifier: License :: OSI Approved :: MIT License
Classifier: Programming Language :: Python :: 3.10
Requires-Python: >=3.10.10
License-File: License
Requires-Dist: httpx
Requires-Dist: loguru
Requires-Dist: bs4
Requires-Dist: fire
